CognxCore/__init__.py
CognxCore/cognx.py
CognxCore-0.25.dist-info/LICENSE.txt
CognxCore-0.25.dist-info/METADATA
CognxCore-0.25.dist-info/WHEEL
CognxCore-0.25.dist-info/top_level.txt
CognxCore-0.25.dist-info/RECORD
